serm/__init__.py
serm/serm.py
serm/sparseae.py
serm-1.0.4.dist-info/LICENSE
serm-1.0.4.dist-info/METADATA
serm-1.0.4.dist-info/WHEEL
serm-1.0.4.dist-info/top_level.txt
serm-1.0.4.dist-info/RECORD
