Metadata-Version: 2.1
Name: serm
Version: 1.0.4
Summary: SERM is a high-performance data-driven gene expression recovery framework.
Home-page: https://github.com/xinglab-ai/self-consistent-expression-recovery-machine
Author: Md Tauhidul Islam
Author-email: tauhid@stanford.edu
Classifier: Programming Language :: Python :: 3
Classifier: License :: OSI Approved :: GNU General Public License v2 (GPLv2)
Classifier: Operating System :: OS Independent
Requires-Python: >=3.8
License-File: LICENSE
Requires-Dist: h5py (==3.6.0)
Requires-Dist: matplotlib (==3.5.0)
Requires-Dist: numpy (==1.22.0)
Requires-Dist: torch (==2.0.1)
Requires-Dist: scikit-learn (==1.0.2)
Requires-Dist: scipy (==1.9.3)
Requires-Dist: torchaudio (==2.0.2)
Requires-Dist: torchvision (==0.15.2)
Requires-Dist: tqdm (==4.62.3)
Requires-Dist: numba
